{
"type": "FeatureCollection",
"crs": { "type": "name", "properties": { "name": "urn:ogc:def:crs:OGC:1.3:CRS84" } },
                                                                                
"features": [
{ "type": "Feature", "properties": { "type": "start" }, "geometry": { "type": "Point", "coordinates": [ -104.75820231835722, 38.869199488951395 ] } },
{ "type": "Feature", "properties": { "type": "direction" }, "geometry": { "type": "Point", "coordinates": [ -104.763715485506111, 38.874266825945725 ] } },
{ "type": "Feature", "properties": { "type": "water" }, "geometry": { "type": "Point", "coordinates": [ -104.764881024755041, 38.874954371923565 ] } },
{ "type": "Feature", "properties": { "type": "direction" }, "geometry": { "type": "Point", "coordinates": [ -104.765833177880324, 38.875346047405536 ] } },
{ "type": "Feature", "properties": { "type": "direction" }, "geometry": { "type": "Point", "coordinates": [ -104.764332369352175, 38.872426544068595 ] } },
{ "type": "Feature", "properties": { "type": "water" }, "geometry": { "type": "Point", "coordinates": [ -104.764442951334786, 38.872190243842127 ] } },
{ "type": "Feature", "properties": { "type": "direction" }, "geometry": { "type": "Point", "coordinates": [ -104.76899411289412, 38.873545991768637 ] } },
{ "type": "Feature", "properties": { "type": "water" }, "geometry": { "type": "Point", "coordinates": [ -104.768945286826067, 38.873553524961856 ] } },
{ "type": "Feature", "properties": { "type": "water" }, "geometry": { "type": "Point", "coordinates": [ -104.767078977793403, 38.871201751353311 ] } },
{ "type": "Feature", "properties": { "type": "direction" }, "geometry": { "type": "Point", "coordinates": [ -104.764623339393268, 38.871514909673976 ] } },
{ "type": "Feature", "properties": { "type": "water" }, "geometry": { "type": "Point", "coordinates": [ -104.76366873874565, 38.870197305558584 ] } },
{ "type": "Feature", "properties": { "type": "direction" }, "geometry": { "type": "Point", "coordinates": [ -104.762424502543197, 38.870152817274011 ] } },
{ "type": "Feature", "properties": { "type": "proposed" }, "geometry": { "type": "Point", "coordinates": [ -104.762848604161292, 38.86955474090329 ] } },
{ "type": "Feature", "properties": { "type": "register" }, "geometry": { "type": "Point", "coordinates": [ -104.759736613883391, 38.868781681880826 ] } },
{ "type": "Feature", "properties": { "type": "finish" }, "geometry": { "type": "Point", "coordinates": [ -104.761720388301512, 38.869842376424536 ] } },
{ "type": "Feature", "properties": { "type": "vendors" }, "geometry": { "type": "Point", "coordinates": [ -104.761249142279709, 38.869759966023096 ] } }
]
}
